pybullet.cp35-win32.pyd
pybullet-1.2.4.dist-info/DESCRIPTION.rst
pybullet-1.2.4.dist-info/METADATA
pybullet-1.2.4.dist-info/RECORD
pybullet-1.2.4.dist-info/WHEEL
pybullet-1.2.4.dist-info/metadata.json
pybullet-1.2.4.dist-info/top_level.txt
pybullet_envs/__init__.py
pybullet_envs/env_bases.py
pybullet_envs/gym_locomotion_envs.py
pybullet_envs/gym_pendulum_envs.py
pybullet_envs/kerasrl_utils.py
pybullet_envs/robot_bases.py
pybullet_envs/robot_locomotors.py
pybullet_envs/robot_pendula.py
pybullet_envs/scene_abstract.py
pybullet_envs/scene_stadium.py
pybullet_envs/bullet/__init__.py
pybullet_envs/bullet/cartpole_bullet.py
pybullet_envs/bullet/kuka.py
pybullet_envs/bullet/kukaCamGymEnv.py
pybullet_envs/bullet/kukaGymEnv.py
pybullet_envs/bullet/minitaur.py
pybullet_envs/bullet/minitaurGymEnv.py
pybullet_envs/bullet/minitaur_bullet.py
pybullet_envs/bullet/minitaur_new.py
pybullet_envs/bullet/racecar.py
pybullet_envs/bullet/racecarGymEnv.py
pybullet_envs/bullet/racecarZEDGymEnv.py
pybullet_envs/bullet/simpleHumanoid.py
pybullet_envs/bullet/simpleHumanoidGymEnv.py
pybullet_envs/data/block.urdf
pybullet_envs/data/cartpole.urdf
pybullet_envs/data/checker_blue.png
pybullet_envs/data/plane.mtl
pybullet_envs/data/plane.obj
pybullet_envs/data/plane.urdf
pybullet_envs/data/sphere2.urdf
pybullet_envs/data/sphere2red.urdf
pybullet_envs/data/sphere_smooth.mtl
pybullet_envs/data/sphere_smooth.obj
pybullet_envs/data/stadium.sdf
pybullet_envs/data/textured_sphere_smooth.mtl
pybullet_envs/data/textured_sphere_smooth.obj
pybullet_envs/data/kuka_iiwa/kuka_with_gripper.sdf
pybullet_envs/data/kuka_iiwa/kuka_with_gripper2.sdf
pybullet_envs/data/kuka_iiwa/kuka_world.sdf
pybullet_envs/data/kuka_iiwa/model.sdf
pybullet_envs/data/kuka_iiwa/model.urdf
pybullet_envs/data/kuka_iiwa/model2.sdf
pybullet_envs/data/kuka_iiwa/model_for_sdf.urdf
pybullet_envs/data/kuka_iiwa/model_free_base.urdf
pybullet_envs/data/kuka_iiwa/model_vr_limits.urdf
pybullet_envs/data/kuka_iiwa/meshes/finger_base_left.stl
pybullet_envs/data/kuka_iiwa/meshes/finger_base_right.stl
pybullet_envs/data/kuka_iiwa/meshes/finger_tip_left.stl
pybullet_envs/data/kuka_iiwa/meshes/finger_tip_right.stl
