Metadata-Version: 2.0
Name: pybullet
Version: 1.2.4
Summary: Official Python Interface for the Bullet Physics SDK Robotics Simulator
Home-page: https://github.com/bulletphysics/bullet3
Author: Erwin Coumans, Yunfei Bai, Jasmine Hsu
Author-email: erwincoumans@google.com
License: zlib
Keywords: game development,virtual reality,physics simulation,robotics,collision detection,opengl
Platform: any
Classifier: Development Status :: 5 - Production/Stable
Classifier: License :: OSI Approved :: zlib/libpng License
Classifier: Operating System :: Microsoft :: Windows
Classifier: Operating System :: POSIX :: Linux
Classifier: Operating System :: MacOS
Classifier: Intended Audience :: Science/Research
Classifier: Programming Language :: Python
Classifier: Programming Language :: Python :: 2.7
Classifier: Programming Language :: Python :: 3.4
Classifier: Programming Language :: Python :: 3.5
Classifier: Programming Language :: Python :: 3.6
Classifier: Topic :: Games/Entertainment :: Simulation
Classifier: Framework :: Robot Framework
